{
  "MOVE_SPEED": 2.5,
  "RANGED_MAX_RANGE": 450,
  "WARRIOR_MELEE_RANGE": 90,
  "MAGICGLADIATOR_MELEE_RANGE": 80,
  "MELEE_RANGE_LVL_SCALE_MULT": 0.6,
  "E1_RANGE_ATK_EXPONENT": 1.0,
  "LEVEL_UP_STAT_POINTS": 2,
  "REQ_KILLS_BASE_MULT": 3,
  "REQ_KILLS_EXPONENT": 1.4,
  "REQ_KILLS_SIN_AMP": 0,
  "REBIRTH_BASE_LEVEL": 5,
  "REBIRTH_LEVEL_STEP": 6,
  "REBIRTH_POINTS_PER_LEVEL": 2,
  "LIMIT_LEVEL_TO_REBIRTH_REQ": true,
  "POTION_BUFF_DURATION": 8000,
  "POTION_LIFESTEAL_PERCENT": 0.30,
  "POTION_BLUE_BUFF_DURATION": 10000,
  "POTION_BLUE_CD_MULTIPLIER": 2.5,
  "POTION_RED_DROP_CHANCE": 0.10,
  "POTION_BLUE_DROP_CHANCE": 0.05,
  "GAME_W": 2560,
  "GAME_H": 1024,
  "DEPTH_GROUND_TOP": 0.2,
  "DEPTH_GROUND_BOTTOM": 1.0,
  "GROUND_TOLERANCE": 30,
  "DEAD_BODY_LIFETIME": 3000,
  "DAY_CYCLE_DURATION": 90,
  "GAME_INITIAL_WAVE": 1,
  "GAME_INITIAL_KILLS": 0,
  "GAME_INITIAL_WAVE_ENEMIES": 12,
  "ENEMY_SPAWN_INTERVAL": 250,
  "ENEMY_SCALE_WAVE_MULT": 0.35,
  "ENEMY_SCALE_LVL_MULT": 0.20,
  "ENEMY_SKY_SPEED_MULTIPLIER": 3.0,
  "ENEMY_ATTACK_COOLDOWN_BASE": 30,
  "ENEMY_ATTACK_COOLDOWN_RAND": 15,
  "BOSS_BASE_HP": 500,
  "BOSS_BASE_ATK": 35,
  "BOSS_BASE_SPEED": 0.35,
  "BOSS_BASE_SIZE": 60,
  "BOSS_BASE_COLOR": "#c0392b",
  "BOSS_ATTACK_COOLDOWN": 45,
  "BOSS_WAVE_INTERVAL": 3,
  "BOSS_SPAWN_INCREMENT": 1,
  "BOSS_LASER_CHANNEL_TIME": 60,
  "BOSS_LASER_DAMAGE_INTERVAL": 200,
  "BOSS_LASER_DAMAGE_PER_SEC": 40,
  "BOSS_LASER_DAMAGE_LEVEL_SCALE": 10,
  "BOSS_PROJECTILE_SPEED": 12.0,
  "BOSS_PROJECTILE_HOMING": true,
  "BOSS_PROJECTILE_LIFETIME": 5000,
  "PROJ_HIT_RADIUS_ARROW": 12,
  "PROJ_HIT_RADIUS_BOLT": 10,
  "PROJ_HIT_RADIUS_DEFAULT": 15,
  "CHAT_MESSAGE_DURATION": 5000,
  "CHAT_FADE_OUT_DURATION": 500,
  "NETWORK_ROOM_NAME": "Night-Vibe-Online-Arena-Hardcore",
  "EQUIPMENT_SLOTS": null,
  "GEAR_DROP_RATE": 0.15,
  "GEAR_RARITY_NORMAL": 0.30,
  "GEAR_RARITY_MAGIC": 0.45,
  "GEAR_RARITY_RARE": 0.25,
  "GEAR_STAT_MULTIPLIER": 1.4,
  "GEAR_STAT_VARIANCE": 0.20,
  "GEAR_DROP_ONLY_BOSS": true,
  "CLEAR_ITEMS_ON_START": true
}
